helm_inspect/__init__.py
helm_inspect/integrations/slack.py
helm_inspect/main.py
helm_inspect/utils/__init__.py
helm_inspect/utils/calibration.py
helm_inspect/utils/cli.py
helm_inspect/utils/cluster.py
helm_inspect/utils/constant.py
helm_inspect/utils/drift_check.py
helm_inspect/utils/logger.py
helm_inspect-1.0.0.dist-info/METADATA
helm_inspect-1.0.0.dist-info/WHEEL
helm_inspect-1.0.0.dist-info/entry_points.txt
helm_inspect-1.0.0.dist-info/RECORD
